jupyter_notepad/__init__.py
jupyter_notepad/constants.py
jupyter_notepad/exc.py
jupyter_notepad/file.py
jupyter_notepad/hooks.py
jupyter_notepad/magics.py
jupyter_notepad/repo.py
jupyter_notepad/labextension/jupyter-notepad/package.json
jupyter_notepad/labextension/jupyter-notepad/static/640.792f3f2111cb4b613a51.js
jupyter_notepad/labextension/jupyter-notepad/static/640.792f3f2111cb4b613a51.js.LICENSE.txt
jupyter_notepad/labextension/jupyter-notepad/static/806.c7caa752dc4dc421f61a.js
jupyter_notepad/labextension/jupyter-notepad/static/875.eaa64da7525ce3530c90.js
jupyter_notepad/labextension/jupyter-notepad/static/remoteEntry.25e4fd6f7e293f6bda18.js
jupyter_notepad/labextension/jupyter-notepad/static/style.js
jupyter_notepad/labextension/jupyter-notepad/static/third-party-licenses.json
jupyter_notepad/nbextension/jupyter-notepad.js
jupyter_notepad-0.0.2.data/data/share/jupyter/labextensions/jupyter-notepad/package.json
jupyter_notepad-0.0.2.data/data/share/jupyter/labextensions/jupyter-notepad/static/640.792f3f2111cb4b613a51.js
jupyter_notepad-0.0.2.data/data/share/jupyter/labextensions/jupyter-notepad/static/640.792f3f2111cb4b613a51.js.LICENSE.txt
jupyter_notepad-0.0.2.data/data/share/jupyter/labextensions/jupyter-notepad/static/806.c7caa752dc4dc421f61a.js
jupyter_notepad-0.0.2.data/data/share/jupyter/labextensions/jupyter-notepad/static/875.eaa64da7525ce3530c90.js
jupyter_notepad-0.0.2.data/data/share/jupyter/labextensions/jupyter-notepad/static/remoteEntry.25e4fd6f7e293f6bda18.js
jupyter_notepad-0.0.2.data/data/share/jupyter/labextensions/jupyter-notepad/static/style.js
jupyter_notepad-0.0.2.data/data/share/jupyter/labextensions/jupyter-notepad/static/third-party-licenses.json
jupyter_notepad-0.0.2.data/data/share/jupyter/nbextensions/jupyter-notepad.js
jupyter_notepad-0.0.2.data/data/etc/jupyter/nbconfig/notebook.d/jupyter-notepad.json
jupyter_notepad-0.0.2.data/data/share/jupyter/labextensions/jupyter-notepad/install.json
jupyter_notepad-0.0.2.dist-info/METADATA
jupyter_notepad-0.0.2.dist-info/WHEEL
jupyter_notepad-0.0.2.dist-info/licenses/LICENSE.txt
jupyter_notepad-0.0.2.dist-info/RECORD
