Metadata-Version: 2.3
Name: jupyter_notepad
Version: 0.0.2
Summary: A versioned code editor widget for Jupyter
Project-URL: Homepage, https://github.com/cfeenstra67/jupyter-notepad
Author-email: Cam Feenstra <me@camfeenstra.com>
License: Copyright 2024 Cameron Feenstra
License-File: LICENSE.txt
Keywords: IPython,Jupyter,Widgets
Classifier: Framework :: Jupyter
Classifier: Intended Audience :: Developers
Classifier: Intended Audience :: Science/Research
Classifier: Programming Language :: Python
Classifier: Programming Language :: Python :: 3
Classifier: Programming Language :: Python :: 3.7
Classifier: Programming Language :: Python :: 3.8
Classifier: Programming Language :: Python :: 3.9
Classifier: Programming Language :: Python :: 3.10
Classifier: Programming Language :: Python :: 3.11
Requires-Python: >=3.7
Requires-Dist: aiohttp>=3.0.0
Requires-Dist: blinker>=1.0.0
Requires-Dist: gitpython>=3.0.0
Requires-Dist: ipywidgets>=7.0.0
Provides-Extra: dev
Requires-Dist: build>=1.0.0; extra == 'dev'
Requires-Dist: bump2version==1.*; extra == 'dev'
Requires-Dist: jupyterlab==4.*; extra == 'dev'
Requires-Dist: mypy<2,>=1; extra == 'dev'
Requires-Dist: ruff; extra == 'dev'
Requires-Dist: twine; extra == 'dev'
